auto_markdown_badges/__init__.py
auto_markdown_badges/__main__.py
auto_markdown_badges/cli.py
auto_markdown_badges/custom_typer.py
auto_markdown_badges/utils.py
auto_markdown_badges-0.2.1.dist-info/entry_points.txt
auto_markdown_badges-0.2.1.dist-info/LICENSE
auto_markdown_badges-0.2.1.dist-info/WHEEL
auto_markdown_badges-0.2.1.dist-info/METADATA
auto_markdown_badges-0.2.1.dist-info/RECORD
