Metadata-Version: 2.1
Name: auto-markdown-badges
Version: 0.2.1
Summary: Auto-generated markdown badges.
License: Apache-2.0
Keywords: markdown,badges,cli
Author: Felix Uellendall
Author-email: feluelle@pm.me
Requires-Python: >=3.9,<4.0
Classifier: License :: OSI Approved :: Apache Software License
Classifier: Programming Language :: Python :: 3
Classifier: Programming Language :: Python :: 3.10
Classifier: Programming Language :: Python :: 3.9
Requires-Dist: click-help-colors (>=0.9.1,<0.10.0)
Requires-Dist: simpleicons (>=6.13.0,<7.0.0)
Requires-Dist: typer (>=0.4.0,<0.5.0)
